CHANGES.rst
LICENSE.rst
MANIFEST.in
README.rst
setup.cfg
setup.py
pymatgen_core/__init__.py
pymatgen_core/dao.py
pymatgen_core/core/__init__.py
pymatgen_core/core/lattice.py
pymatgen_core/core/periodic_table.json
pymatgen_core/core/periodic_table.py
pymatgen_core/core/units.py
pymatgen_core/core/tests/__init__.py
pymatgen_core/core/tests/test_lattice.py
pymatgen_core/core/tests/test_periodic_table.py
pymatgen_core/core/tests/test_units.py
pymatgen_core/util/__init__.py
pymatgen_core/util/num.py
pymatgen_core/util/string.py
pymatgen_core/util/tests/__init__.py
streamm/__init__.py
streamm.egg-info/PKG-INFO
streamm.egg-info/SOURCES.txt
streamm.egg-info/dependency_links.txt
streamm.egg-info/top_level.txt
streamm/calculations/__init__.py
streamm/calculations/calculation.py
streamm/calculations/gaussian.py
streamm/calculations/lammps.py
streamm/calculations/nwchem.py
streamm/calculations/project.py
streamm/calculations/resource.py
streamm/calculations/tests/__init__.py
streamm/calculations/tests/streamm_testutil.py
streamm/calculations/tests/test_calculation.py
streamm/calculations/tests/test_gaussian.py
streamm/calculations/tests/test_lammps.py
streamm/calculations/tests/test_nwchem.py
streamm/calculations/tests/test_project.py
streamm/calculations/tests/test_resource.py
streamm/forcefields/__init__.py
streamm/forcefields/angletype.py
streamm/forcefields/bondtype.py
streamm/forcefields/dihtype.py
streamm/forcefields/imptype.py
streamm/forcefields/parameters.py
streamm/forcefields/particletype.py
streamm/forcefields/tests/__init__.py
streamm/forcefields/tests/streamm_testutil.py
streamm/forcefields/tests/test_angletype.py
streamm/forcefields/tests/test_bondtype.py
streamm/forcefields/tests/test_dihtype.py
streamm/forcefields/tests/test_imptype.py
streamm/forcefields/tests/test_parameters.py
streamm/forcefields/tests/test_particletype.py
streamm/mpi/__init__.py
streamm/mpi/mpiBase.py
streamm/structures/__init__.py
streamm/structures/angle.py
streamm/structures/bond.py
streamm/structures/buildingblock.py
streamm/structures/dihedral.py
streamm/structures/group.py
streamm/structures/improper.py
