Metadata-Version: 1.0
Name: streamm
Version: 0.3.2
Summary: The Simulation Toolkit for Renewable Energy and Advanced Materials Modeling (STREAMM)
Home-page: http://streamm.nrel.gov
Author: Ross Larsen
Author-email: streamm@nrel.gov
License: Apache License, Version 2.0
Keywords: NWChem,gaussian,LAMMPS,MD,materials,project,electronic,structure,analysis,coupling,molecular,dynamics,organic,generator,high,throughput,combinatorial,computational,chemistry,functionalization,polymerization
Platform: UNKNOWN
